odoo/addons/account_analytic_tag_default/README.rst
odoo/addons/account_analytic_tag_default/__init__.py
odoo/addons/account_analytic_tag_default/__manifest__.py
odoo/addons/account_analytic_tag_default/i18n/account_analytic_tag_default.pot
odoo/addons/account_analytic_tag_default/i18n/es.po
odoo/addons/account_analytic_tag_default/i18n/pt_BR.po
odoo/addons/account_analytic_tag_default/models/__init__.py
odoo/addons/account_analytic_tag_default/models/account_analytic_account.py
odoo/addons/account_analytic_tag_default/models/account_move.py
odoo/addons/account_analytic_tag_default/readme/CONFIGURE.rst
odoo/addons/account_analytic_tag_default/readme/CONTRIBUTORS.rst
odoo/addons/account_analytic_tag_default/readme/DESCRIPTION.rst
odoo/addons/account_analytic_tag_default/readme/ROADMAP.rst
odoo/addons/account_analytic_tag_default/readme/USAGE.rst
odoo/addons/account_analytic_tag_default/static/description/icon.png
odoo/addons/account_analytic_tag_default/static/description/index.html
odoo/addons/account_analytic_tag_default/tests/__init__.py
odoo/addons/account_analytic_tag_default/tests/test_account_analytic_tag_default.py
odoo/addons/account_analytic_tag_default/views/account_analytic_account_view.xml
odoo_addon_account_analytic_tag_default-15.0.1.1.0.1.dist-info/METADATA
odoo_addon_account_analytic_tag_default-15.0.1.1.0.1.dist-info/WHEEL
odoo_addon_account_analytic_tag_default-15.0.1.1.0.1.dist-info/top_level.txt
odoo_addon_account_analytic_tag_default-15.0.1.1.0.1.dist-info/RECORD
