Metadata-Version: 2.1
Name: odoo-addon-account_analytic_tag_default
Version: 15.0.1.1.0.1
Summary: Set default tags on analytic accounts.
Home-page: https://github.com/OCA/account-analytic
Author: ForgeFlow, Odoo Community Association (OCA)
Author-email: support@odoo-community.org
License: AGPL-3
Classifier: Programming Language :: Python
Classifier: Framework :: Odoo
Classifier: Framework :: Odoo :: 15.0
Classifier: License :: OSI Approved :: GNU Affero General Public License v3
Requires-Python: >=3.8
Requires-Dist: odoo<15.1dev,>=15.0a
